{
  "descriptionHash": "C9B7554BA45E841C29022AC34C1005BD551EE419367395B6796846075300F1339BE67BB044F25FEDDB69C4CDB62AB092E2088D075F50B9CF166888437AEB7EBC",
  "descriptionLocation": "../fixed.json",
  "lockFileVersion": "1.0.0",
  "kiotaVersion": "1.28.0",
  "clientClassName": "CloudflareOpenApiClient",
  "typeAccessModifier": "Public",
  "clientNamespaceName": "Soenneker.Cloudflare.OpenApiClient",
  "language": "CSharp",
  "usesBackingStore": false,
  "excludeBackwardCompatible": false,
  "includeAdditionalData": true,
  "disableSSLValidation": false,
  "serializers": [
    "Microsoft.Kiota.Serialization.Json.JsonSerializationWriterFactory",
    "Microsoft.Kiota.Serialization.Text.TextSerializationWriterFactory",
    "Microsoft.Kiota.Serialization.Form.FormSerializationWriterFactory",
    "Microsoft.Kiota.Serialization.Multipart.MultipartSerializationWriterFactory"
  ],
  "deserializers": [
    "Microsoft.Kiota.Serialization.Json.JsonParseNodeFactory",
    "Microsoft.Kiota.Serialization.Text.TextParseNodeFactory",
    "Microsoft.Kiota.Serialization.Form.FormParseNodeFactory"
  ],
  "structuredMimeTypes": [
    "application/json",
    "text/plain;q=0.9",
    "application/x-www-form-urlencoded;q=0.2",
    "multipart/form-data;q=0.1"
  ],
  "includePatterns": [],
  "excludePatterns": [],
  "disabledValidationRules": []
}