{
  "descriptionHash": "66A7B6682DAFC59F180532F7707D5E539F5EC6DC95D4822C5D05052E67BD875CEDA099F20563F32A1DBCA3154F9DEBBC49B35055A18D8EEEFC9304EE94FE6D59",
  "descriptionLocation": "../fixed.json",
  "lockFileVersion": "1.0.0",
  "kiotaVersion": "1.28.0",
  "clientClassName": "CloudflareOpenApiClient",
  "typeAccessModifier": "Public",
  "clientNamespaceName": "Soenneker.Cloudflare.OpenApiClient",
  "language": "CSharp",
  "usesBackingStore": false,
  "excludeBackwardCompatible": true,
  "includeAdditionalData": true,
  "disableSSLValidation": false,
  "serializers": [
    "Microsoft.Kiota.Serialization.Json.JsonSerializationWriterFactory",
    "Microsoft.Kiota.Serialization.Text.TextSerializationWriterFactory",
    "Microsoft.Kiota.Serialization.Form.FormSerializationWriterFactory",
    "Microsoft.Kiota.Serialization.Multipart.MultipartSerializationWriterFactory"
  ],
  "deserializers": [
    "Microsoft.Kiota.Serialization.Json.JsonParseNodeFactory",
    "Microsoft.Kiota.Serialization.Text.TextParseNodeFactory",
    "Microsoft.Kiota.Serialization.Form.FormParseNodeFactory"
  ],
  "structuredMimeTypes": [
    "application/json",
    "text/plain;q=0.9",
    "application/x-www-form-urlencoded;q=0.2",
    "multipart/form-data;q=0.1"
  ],
  "includePatterns": [],
  "excludePatterns": [],
  "disabledValidationRules": []
}